dtools/queues/__init__.py
dtools/queues/de.py
dtools/queues/fifo.py
dtools/queues/lifo.py
dtools/queues/py.typed
dtools_queues-2.0.0.dist-info/licenses/LICENSE
dtools_queues-2.0.0.dist-info/WHEEL
dtools_queues-2.0.0.dist-info/METADATA
dtools_queues-2.0.0.dist-info/RECORD
